
{
    "name": "nsd:trial_tower/golem_room",
    "fallback": "minecraft:empty",
    "elements": [
    {
        "weight": 1,
        "element": {
            "location": "nsd:trial_tower/golem_room_1",
            "processors": "nsd:trial_tower",
            "projection": "rigid",
            "element_type": "minecraft:single_pool_element"
        }
    },
    {
        "weight": 1,
        "element": {
            "location": "nsd:trial_tower/golem_room_2",
            "processors": "nsd:trial_tower",
            "projection": "rigid",
            "element_type": "minecraft:single_pool_element"
        }
    },
    {
        "weight": 1,
        "element": {
            "location": "nsd:trial_tower/golem_room_3",
            "processors": "nsd:trial_tower",
            "projection": "rigid",
            "element_type": "minecraft:single_pool_element"
        }
    },
    {
        "weight": 1,
        "element": {
            "location": "nsd:trial_tower/golem_room_4",
            "processors": "nsd:trial_tower",
            "projection": "rigid",
            "element_type": "minecraft:single_pool_element"
        }
    },
    {
        "weight": 1,
        "element": {
            "location": "nsd:trial_tower/golem_room_5",
            "processors": "nsd:trial_tower",
            "projection": "rigid",
            "element_type": "minecraft:single_pool_element"
        }
    },
    {
        "weight": 3,
        "element": {
            "location": "nsd:trial_tower/side_room_11",
            "processors": "nsd:trial_tower",
            "projection": "rigid",
            "element_type": "minecraft:single_pool_element"
        }
    },
    {
        "weight": 1,
        "element": {
            "location": "nsd:trial_tower/golem_room_6",
            "processors": "nsd:trial_tower",
            "projection": "rigid",
            "element_type": "minecraft:single_pool_element"
        }
    }
]
}